LM07.v
//Define
`define TEMP_SET  16'h3100

module LM07(CS, SCK, SIO);
  output SIO;
  input SCK, CS;

  reg [15:0] shift_reg;
  wire clk_gated;

  initial begin
    shift_reg = `TEMP_SET; 
  end
  
  assign SIO = shift_reg[15];

  assign clk_gated = ~CS & SCK;

  always @(CS)
   begin
     shift_reg = `TEMP_SET;
   end

  always @(negedge clk_gated)
    begin
      shift_reg = shift_reg<<1;
    end
endmodule

bin2BCD.v
module bin2BCD(bin,BCD1,BCD2,reset,clk);
  input  [6:0] bin;
  output [3:0] BCD1;
  output [3:0] BCD2;
  input clk;
  input reset;
  reg [3:0] bcd_2 = 4'b0;
  reg [3:0] bcd_1 = 4'b0; 
  reg [4:0] binary;
  
  parameter start   = 0;
  parameter shift_1 = 1;
  parameter check_1 = 2;
  parameter add_1   = 3;
  parameter shift_2 = 4;
  parameter check_2 = 5;
  parameter add_2   = 6;
  parameter shift_3 = 7;
  parameter check_3 = 8;
  parameter add_3   = 9; 
  parameter shift_4 = 10;
  parameter check_4 = 11;
  parameter add_4   = 12;
  parameter shift_5 = 13;
  
  reg [3:0] state;
  reg [3:0] next_state;
  


  always@(posedge clk, ~reset) begin
    if (~reset) begin
      state <= start;
      binary <= bin[4:0];
    end
    else begin 
      state <= next_state;
    end
  end
  
  always@(state) begin
    case (state) 
      start   : begin 
                bcd_1 <= {1'b0,1'b0,bin[6:5]};
                bcd_2 <= 4'b0;
                next_state <= shift_1;
                end
      shift_1 : begin
                bcd_2 <= {bcd_2[2:0],bcd_1[3]};
                bcd_1 <= {bcd_1[2:0],binary[4]};
                binary <= {binary[3:0],1'b0};
                next_state <= check_1;
                end
      check_1 : begin
                if (bcd_1 > 4'b0100) begin
                  next_state <= add_1;
                end
                else next_state <= shift_2;
                end
      add_1   : begin
                bcd_1 <= bcd_1 + 4'b0011;
                next_state <= shift_2;
                end
      shift_2 : begin
                bcd_2 <= {bcd_2[2:0],bcd_1[3]};
                bcd_1 <= {bcd_1[2:0],binary[4]};
                binary <= {binary[3:0],1'b0};
                next_state <= check_2;
                end
      check_2 : begin
                if (bcd_1 > 4'b0100) begin
                  next_state <= add_2;
                end
                else next_state <= shift_3;
                end
      add_2   : begin
                bcd_1 <= bcd_1 + 4'b0011;
                next_state <= shift_3;
                end
      shift_3 : begin
                bcd_2 <= {bcd_2[2:0],bcd_1[3]};
                bcd_1 <= {bcd_1[2:0],binary[4]};
                binary <= {binary[3:0],1'b0};
                next_state <= check_3;
                end
      check_3 : begin
                if (bcd_1 > 4'b0100) begin
                  next_state <= add_3;
                end
                else next_state <= shift_4;
                end
      add_3   : begin
                bcd_1 <= bcd_1 + 4'b0011;
                next_state <= shift_4;
                end
      shift_4 : begin
                bcd_2 <= {bcd_2[2:0],bcd_1[3]};
                bcd_1 <= {bcd_1[2:0],binary[4]};
                binary <= {binary[3:0],1'b0};
                next_state <= check_4;
                end
      check_4 : begin
                if (bcd_1 > 4'b0100) begin
                  next_state <= add_4;
                end
                else next_state <= shift_5;
                end
      add_4   : begin
                bcd_1 <= bcd_1 + 4'b0011;
                next_state <= shift_5;
                end
      shift_5 : begin
                bcd_2 <= {bcd_2[2:0],bcd_1[3]};
                bcd_1 <= {bcd_1[2:0],binary[4]};
                binary <= {binary[3:0],1'b0};
                end
    endcase
  end
  assign BCD1 = bcd_1;
  assign BCD2 = bcd_2;
endmodule

LM07_read.v
`include "bin2BCD.v"


//DEFINES
`define CS_LOW_COUNT    5'd10 
`define CS_HIGH_COUNT   5'd28
`define CS_initial      1'b1;
`define SCK_initial     1'b1;

module LM07_read(RSTN,SYSCLK,SIO,CS,SEL0,SEL1,SCK,data_latched,displayLSB,displayMSB);

input RSTN,SYSCLK,SIO;
output reg CS  = `CS_initial;
output reg SCK =`SCK_initial;
output SEL0;
output SEL1;
output reg [7:0] data_latched;

reg [3:0] count_SCK=4'd0;
reg [4:0] count=1'b1;
reg [7:0] data_out;
reg chk_state;                          //remove output
reg RSTN_BCD = 1'b1;                    //remove output
output wire [3:0] displayLSB;           //remove output
output wire [3:0] displayMSB;           //remove output

bin2BCD b2B(data_latched[6:0],displayLSB,displayMSB,RSTN_BCD,SYSCLK);

always@(posedge SYSCLK) begin
    count <= count+1;
    if (count == `CS_LOW_COUNT) begin
        CS <= 1'b0;
        chk_state <= 1'b0;
        data_out <= 8'b0;
        count_SCK <= 4'd0;
        
    end
    else if (count == `CS_HIGH_COUNT) begin
        CS <=1'b1;
        count <= 1'b0;
        data_out <= 8'd0;
    end
    
end

always@(negedge SYSCLK , negedge RSTN) begin
    if (CS) begin
        SCK <= 1'b0;
    end
    else if (CS == 1'b0)begin
        SCK <= ~SCK;
    end
    if (SCK == 1'b1) begin
        RSTN_BCD <= 1'b1;
    end
end

always@(posedge SCK) begin
        count_SCK <= count_SCK + 1;
        data_out    = data_out<<1;                   // to negate the 15th bit from temp sensor since our sensor counts from 00-99 with one sign bit so essentially 8 bits from which 7 bits are for temp sensor and one bit for sign
        data_out[0] = SIO;
        if (count_SCK == 4'd8) begin                 //to count the SCK for latching out the data just before the end of the last read cycle 
            chk_state <= 1'b1;
        end
end

always@(posedge chk_state) begin
    data_latched <= data_out;
    if (chk_state == 1'b1) begin
        RSTN_BCD <= 1'b0;
    end
end

always@(negedge chk_state) begin
    data_latched <= 8'd0;
end

endmodule

tb_LM07.v
`timescale 1ns/1ps

`include "LM07.v"

module tb();
wire CS,SCK;
wire SEL0,SEL1;
reg RSTN,SYSCLK;
wire SIO;
wire [7:0] data_latched;
wire [3:0] displayLSB;
wire [3:0] displayMSB;

LM07_read lm(RSTN,SYSCLK,SIO,CS,SEL0,SEL1,SCK,data_latched,displayLSB,displayMSB);
LM07 lm1(CS,SCK,SIO);

always #5 SYSCLK <= ~SYSCLK;

initial begin
    $dumpfile("dump.vcd");
    $dumpvars(1);
    RSTN = 1'b0;
    SYSCLK = 1'b0;
    #5 RSTN = 1'b1;
    #800 $finish;
end
endmodule

dump.vcd
$date
	Sun Mar 26 12:53:52 2023
$end
$version
	Icarus Verilog
$end
$timescale
	1ps
$end
$scope module tb $end
$var wire 1 ! SEL0 $end
$var wire 1 " SEL1 $end
$var wire 4 # displayMSB [3:0] $end
$var wire 4 $ displayLSB [3:0] $end
$var wire 8 % data_latched [7:0] $end
$var wire 1 & SIO $end
$var wire 1 ' SCK $end
$var wire 1 ( CS $end
$var reg 1 ) RSTN $end
$var reg 1 * SYSCLK $end
$upscope $end
$enddefinitions $end
$comment Show the parameter values. $end
$dumpall
$end
#0
$dumpvars
0*
0)
1(
0'
0&
bx %
b0 $
b0 #
z"
z!
$end
#5000
1*
1)
#10000
0*
#15000
1*
#20000
0*
#25000
1*
#30000
0*
#35000
1*
#40000
0*
#45000
1*
#50000
0*
#55000
1*
#60000
0*
#65000
1*
#70000
0*
#75000
1*
#80000
0*
#85000
1*
#90000
0*
#95000
b0 %
0(
1*
#100000
1'
0*
#105000
1*
#110000
0'
0*
#115000
1*
#120000
1'
0*
#125000
1*
#130000
1&
0'
0*
#135000
1*
#140000
1'
0*
#145000
1*
#150000
0'
0*
#155000
1*
#160000
1'
0*
#165000
1*
#170000
0&
0'
0*
#175000
1*
#180000
1'
0*
#185000
1*
#190000
0'
0*
#195000
1*
#200000
1'
0*
#205000
1*
#210000
0'
0*
#215000
1*
#220000
1'
0*
#225000
1*
#230000
1&
0'
0*
#235000
1*
#240000
1'
0*
#245000
1*
#250000
0&
0'
0*
#255000
1*
#260000
b11 $
b1100010 %
1'
0*
#265000
1*
#270000
b110 $
0'
0*
#275000
1(
1*
#280000
0*
#285000
b1001 $
1*
#290000
0*
#295000
b10 $
b1 #
1*
#300000
0*
#305000
1*
#310000
0*
#315000
b100 $
b10 #
1*
#320000
0*
#325000
1*
#330000
0*
#335000
b1001 $
b100 #
1*
#340000
0*
#345000
1*
#350000
0*
#355000
b1100 $
1*
#360000
0*
#365000
b1000 $
b1001 #
1*
#370000
0*
#375000
1*
#380000
0*
#385000
b0 %
0(
1*
#390000
1'
0*
#395000
1*
#400000
0'
0*
#405000
1*
#410000
1'
0*
#415000
1*
#420000
1&
0'
0*
#425000
1*
#430000
1'
0*
#435000
1*
#440000
0'
0*
#445000
1*
#450000
1'
0*
#455000
1*
#460000
0&
0'
0*
#465000
1*
#470000
1'
0*
#475000
1*
#480000
0'
0*
#485000
1*
#490000
1'
0*
#495000
1*
#500000
0'
0*
#505000
1*
#510000
1'
0*
#515000
1*
#520000
1&
0'
0*
#525000
1*
#530000
1'
0*
#535000
1*
#540000
0&
0'
0*
#545000
1*
#550000
b0 #
b11 $
b1100010 %
1'
0*
#555000
1*
#560000
b110 $
0'
0*
#565000
1(
1*
#570000
0*
#575000
b1001 $
1*
#580000
0*
#585000
b10 $
b1 #
1*
#590000
0*
#595000
1*
#600000
0*
#605000
b100 $
b10 #
1*
#610000
0*
#615000
1*
#620000
0*
#625000
b1001 $
b100 #
1*
#630000
0*
#635000
1*
#640000
0*
#645000
b1100 $
1*
#650000
0*
#655000
b1000 $
b1001 #
1*
#660000
0*
#665000
1*
#670000
0*
#675000
b0 %
0(
1*
#680000
1'
0*
#685000
1*
#690000
0'
0*
#695000
1*
#700000
1'
0*
#705000
1*
#710000
1&
0'
0*
#715000
1*
#720000
1'
0*
#725000
1*
#730000
0'
0*
#735000
1*
#740000
1'
0*
#745000
1*
#750000
0&
0'
0*
#755000
1*
#760000
1'
0*
#765000
1*
#770000
0'
0*
#775000
1*
#780000
1'
0*
#785000
1*
#790000
0'
0*
#795000
1*
#800000
1'
0*
