LM07.v
//Define
`define TEMP_SET  16'h3100

module LM07(CS, SCK, SIO);
  output SIO;
  input SCK, CS;

  reg [15:0] shift_reg;
  wire clk_gated;

  initial begin
    shift_reg = `TEMP_SET; 
  end
  
  assign SIO = shift_reg[15];

  assign clk_gated = ~CS & SCK;

  always @(CS)
   begin
     shift_reg = `TEMP_SET;
   end

  always @(negedge clk_gated)
    begin
      shift_reg = shift_reg<<1;
    end
endmodule

seve_seg.v
module seve_seg(A,out,cs,clear);
  
  input [3:0] A;
  output reg [6:0] out;
  input cs;
  input clear;
  always@(A,cs) begin
    if (~clear) begin
  if (~cs) begin
      case ({A})
        4'b0000 :  out = 7'h3f;
        4'b0001 :  out = 7'h06;
        4'b0010 :  out = 7'h5b;
        4'b0011 :  out = 7'h4f;
        4'b0100 :  out = 7'h66;
        4'b0101 :  out = 7'h6d;
        4'b0110 :  out = 7'h7d;
        4'b0111 :  out = 7'h07;
        4'b1000 :  out = 7'h7f;
        4'b1001 :  out = 7'h6f;
      endcase
  end
    end
    else out = 7'h00;
  end
endmodule

bin2BCD.v
module bin2BCD(bin,BCD1,BCD2,reset,clk);
  input  [6:0] bin;
  output [3:0] BCD1;
  output [3:0] BCD2;
  input clk;
  input reset;
  reg [3:0] bcd_2 = 4'b0;
  reg [3:0] bcd_1 = 4'b0; 
  reg [4:0] binary;
  
  parameter start   = 0;
  parameter shift_1 = 1;
  parameter check_1 = 2;
  parameter add_1   = 3;
  parameter shift_2 = 4;
  parameter check_2 = 5;
  parameter add_2   = 6;
  parameter shift_3 = 7;
  parameter check_3 = 8;
  parameter add_3   = 9; 
  parameter shift_4 = 10;
  parameter check_4 = 11;
  parameter add_4   = 12;
  parameter shift_5 = 13;
  
  reg [3:0] state;
  reg [3:0] next_state;
  


  always@(posedge clk, ~reset) begin
    if (~reset) begin
      state <= start;
      binary <= bin[4:0];
    end
    else begin 
      state <= next_state;
    end
  end
  
  always@(state) begin
    case (state) 
      start   : begin 
                bcd_1 <= {1'b0,1'b0,bin[6:5]};
                bcd_2 <= 4'b0;
                next_state <= shift_1;
                end
      shift_1 : begin
                bcd_2 <= {bcd_2[2:0],bcd_1[3]};
                bcd_1 <= {bcd_1[2:0],binary[4]};
                binary <= {binary[3:0],1'b0};
                next_state <= check_1;
                end
      check_1 : begin
                if (bcd_1 > 4'b0100) begin
                  next_state <= add_1;
                end
                else next_state <= shift_2;
                end
      add_1   : begin
                bcd_1 <= bcd_1 + 4'b0011;
                next_state <= shift_2;
                end
      shift_2 : begin
                bcd_2 <= {bcd_2[2:0],bcd_1[3]};
                bcd_1 <= {bcd_1[2:0],binary[4]};
                binary <= {binary[3:0],1'b0};
                next_state <= check_2;
                end
      check_2 : begin
                if (bcd_1 > 4'b0100) begin
                  next_state <= add_2;
                end
                else next_state <= shift_3;
                end
      add_2   : begin
                bcd_1 <= bcd_1 + 4'b0011;
                next_state <= shift_3;
                end
      shift_3 : begin
                bcd_2 <= {bcd_2[2:0],bcd_1[3]};
                bcd_1 <= {bcd_1[2:0],binary[4]};
                binary <= {binary[3:0],1'b0};
                next_state <= check_3;
                end
      check_3 : begin
                if (bcd_1 > 4'b0100) begin
                  next_state <= add_3;
                end
                else next_state <= shift_4;
                end
      add_3   : begin
                bcd_1 <= bcd_1 + 4'b0011;
                next_state <= shift_4;
                end
      shift_4 : begin
                bcd_2 <= {bcd_2[2:0],bcd_1[3]};
                bcd_1 <= {bcd_1[2:0],binary[4]};
                binary <= {binary[3:0],1'b0};
                next_state <= check_4;
                end
      check_4 : begin
                if (bcd_1 > 4'b0100) begin
                  next_state <= add_4;
                end
                else next_state <= shift_5;
                end
      add_4   : begin
                bcd_1 <= bcd_1 + 4'b0011;
                next_state <= shift_5;
                end
      shift_5 : begin
                bcd_2 <= {bcd_2[2:0],bcd_1[3]};
                bcd_1 <= {bcd_1[2:0],binary[4]};
                binary <= {binary[3:0],1'b0};
                end
    endcase
  end
  assign BCD1 = bcd_1;
  assign BCD2 = bcd_2;
endmodule

LM07_read.v
`include "bin2BCD.v"
`include "seve_seg.v"

//DEFINES
`define CS_LOW_COUNT    5'd12 
`define CS_HIGH_COUNT   5'd30
`define CS_initial      1'b1
`define SCK_initial     1'b1

module LM07_read(RSTN,SYSCLK,SIO,CS,disp,SCK,data,chk_state,if_done);

input RSTN,SYSCLK,SIO;
output reg CS  = `CS_initial;
output reg SCK =`SCK_initial;
output [1:0] disp;               // to choose the 7 segment display
reg [7:0] data_latched;         //remove output
output [7:0] data;              //final output
//output [7:0] data_disp;         //final output through decoder

reg SEL_EN = 1'b1;               // to choose 7 segment display selection process of disp
wire [3:0] display_data;
reg [3:0] count_SCK=4'd0;
reg [4:0] count=1'b1;
reg [7:0] data_out;
output reg chk_state;                   //remove output
reg RSTN_BCD = 1'b1;             //remove output
wire [3:0] displayLSB;           //remove output
wire [3:0] displayMSB;           //remove output
output wire if_done;             //remove output

bin2BCD b2B(data_latched[6:0],displayLSB,displayMSB,RSTN_BCD,SYSCLK,if_done);
seve_seg sg();

always@(posedge SYSCLK) begin
    count <= count+1;
    if (count == `CS_LOW_COUNT) begin
        CS <= 1'b0;
        chk_state <= 1'b0;
        data_out <= 8'b0;
        count_SCK <= 4'd0;
        
    end
    else if (count == `CS_HIGH_COUNT) begin
        CS <=1'b1;
        count <= 1'b0;
        data_out <= 8'd0;
    end
    
end

always@(negedge SYSCLK , negedge RSTN) begin
    if (CS) begin
        SCK <= 1'b0;
    end
    else if (CS == 1'b0)begin
        SCK <= ~SCK;
    end
    if (SCK == 1'b1) begin
        RSTN_BCD <= 1'b1;
    end
end

always@(posedge SYSCLK) begin
    SEL_EN <= ~SEL_EN;
end

always@(posedge SCK) begin
        count_SCK <= count_SCK + 1;
        data_out    = data_out<<1;                   // to negate the 15th bit from temp sensor since our sensor counts from 00-99 with one sign bit so essentially 8 bits from which 7 bits are for temp sensor and one bit for sign
        data_out[0] = SIO;
        if (count_SCK == 4'd8) begin                 //to count the SCK for latching out the data just before the end of the last read cycle 
            chk_state <= 1'b1;
        end
end

always@(posedge chk_state) begin
    data_latched <= data_out;
    if (chk_state == 1'b1) begin
        RSTN_BCD <= 1'b0;
    end
end

always@(negedge chk_state) begin
    data_latched <= 8'd0;
end


assign disp[0] = ((if_done == 1'b1) && (SEL_EN == 1'b0) && (CS == 1'b1)) ? 1'b1 : 1'b0;
assign disp[1] = ((if_done == 1'b1) && (SEL_EN == 1'b1) && (CS == 1'b1)) ? 1'b1 : 1'b0;
assign display_data = (disp[1]== 1'b1) ? displayMSB : displayLSB;
assign data[7:4] = displayMSB;
assign data[3:0] = display_data;
endmodule

tb_LM07.v
`timescale 1ns/1ps

`include "LM07.v"

module tb();
wire CS,SCK;
wire SEL0,SEL1;
reg RSTN,SYSCLK;
wire SIO;
wire [1:0] disp;
wire [7:0] data;
//wire [7:0] data_disp;
wire chk_state;
wire if_done;

LM07_read lm(RSTN,SYSCLK,SIO,CS,disp,SCK,data,chk_state,if_done);
LM07 lm1(CS,SCK,SIO);

always #5 SYSCLK <= ~SYSCLK;

initial begin
    $dumpfile("dump.vcd");
    $dumpvars(1);
    RSTN = 1'b0;
    SYSCLK = 1'b0;
    #5 RSTN = 1'b1;
    #800 $finish;
end
endmodule

dump.vcd
$date
	Thu Mar 30 07:27:47 2023
$end
$version
	Icarus Verilog
$end
$timescale
	1ps
$end
$scope module tb $end
$var wire 1 ! if_done $end
$var wire 2 " disp [1:0] $end
$var wire 8 # data [7:0] $end
$var wire 1 $ chk_state $end
$var wire 1 % SIO $end
$var wire 1 & SCK $end
$var wire 1 ' CS $end
$var reg 1 ( RSTN $end
$var reg 1 ) SYSCLK $end
$upscope $end
$enddefinitions $end
$comment Show the parameter values. $end
$dumpall
$end
#0
$dumpvars
0)
0(
1'
0&
1%
x$
b0 #
bx0 "
x!
$end
#5000
b0x "
1)
1(
#10000
0)
#15000
bx0 "
1)
#20000
0)
#25000
b0x "
1)
#30000
0)
#35000
bx0 "
1)
#40000
0)
#45000
b0x "
1)
#50000
0)
#55000
bx0 "
1)
#60000
0)
#65000
b0x "
1)
#70000
0)
#75000
bx0 "
1)
#80000
0)
#85000
b0x "
1)
#90000
0)
#95000
bx0 "
1)
#100000
0)
#105000
b0x "
1)
#110000
0)
#115000
b0 "
0%
0$
0'
1)
#120000
1&
0)
#125000
1)
#130000
1%
0&
0)
#135000
1)
#140000
1&
0)
#145000
1)
#150000
0&
0)
#155000
1)
#160000
1&
0)
#165000
1)
#170000
0%
0&
0)
#175000
1)
#180000
1&
0)
#185000
1)
#190000
0&
0)
#195000
1)
#200000
1&
0)
#205000
1)
#210000
1%
0&
0)
#215000
1)
#220000
1&
0)
#225000
1)
#230000
0%
0&
0)
#235000
1)
#240000
1&
0)
#245000
1)
#250000
1%
0&
0)
#255000
1)
#260000
1&
0)
#265000
1)
#270000
0&
0)
#275000
1)
#280000
b10 #
0!
1$
1&
0)
#285000
1)
#290000
b100 #
0&
0)
#295000
0%
1'
1)
#300000
0)
#305000
b1001 #
1)
#310000
0)
#315000
1)
#320000
0)
#325000
b1100 #
1)
#330000
0)
#335000
b11000 #
1)
#340000
0)
#345000
1)
#350000
0)
#355000
b11011 #
1)
#360000
0)
#365000
b110111 #
1)
#370000
0)
#375000
1)
#380000
0)
#385000
b111010 #
1)
#390000
0)
#395000
b10 "
1!
b1110111 #
1)
#400000
0)
#405000
b1110101 #
b1 "
1)
#410000
0)
#415000
b1110111 #
b10 "
1)
#420000
0)
#425000
b1110101 #
b0 "
0$
0'
1)
#430000
1&
0)
#435000
1)
#440000
1%
0&
0)
#445000
1)
#450000
1&
0)
#455000
1)
#460000
0&
0)
#465000
1)
#470000
1&
0)
#475000
1)
#480000
0%
0&
0)
#485000
1)
#490000
1&
0)
#495000
1)
#500000
0&
0)
#505000
1)
#510000
1&
0)
#515000
1)
#520000
1%
0&
0)
#525000
1)
#530000
1&
0)
#535000
1)
#540000
0%
0&
0)
#545000
1)
#550000
1&
0)
#555000
1)
#560000
1%
0&
0)
#565000
1)
#570000
1&
0)
#575000
1)
#580000
0&
0)
#585000
1)
#590000
0!
b10 #
1$
1&
0)
#595000
1)
#600000
b100 #
0&
0)
#605000
0%
1'
1)
#610000
0)
#615000
b1001 #
1)
#620000
0)
#625000
1)
#630000
0)
#635000
b1100 #
1)
#640000
0)
#645000
b11000 #
1)
#650000
0)
#655000
1)
#660000
0)
#665000
b11011 #
1)
#670000
0)
#675000
b110111 #
1)
#680000
0)
#685000
1)
#690000
0)
#695000
b111010 #
1)
#700000
0)
#705000
b1 "
1!
b1110101 #
1)
#710000
0)
#715000
b1110111 #
b10 "
1)
#720000
0)
#725000
b1110101 #
b1 "
1)
#730000
0)
#735000
b0 "
0$
0'
1)
#740000
1&
0)
#745000
1)
#750000
1%
0&
0)
#755000
1)
#760000
1&
0)
#765000
1)
#770000
0&
0)
#775000
1)
#780000
1&
0)
#785000
1)
#790000
0%
0&
0)
#795000
1)
#800000
1&
0)
