LM07.v
//Define
`define TEMP_SET  16'h3100

module LM07(CS, SCK, SIO);
  output SIO;
  input SCK, CS;

  reg [15:0] shift_reg;
  wire clk_gated;

  initial begin
    shift_reg = `TEMP_SET; 
  end
  
  assign SIO = shift_reg[15];

  assign clk_gated = ~CS & SCK;

  always @(CS)
   begin
     shift_reg = `TEMP_SET;
   end

  always @(negedge clk_gated)
    begin
      shift_reg = shift_reg<<1;
    end
endmodule

bin2BCD.v
module bin2BCD(bin,BCD1,BCD2,reset,clk,if_done);
  input  [6:0] bin;
  output [3:0] BCD1;
  output [3:0] BCD2;
  output reg if_done;                   //to prevent fluctuations in displaying through 7 seg display, it acknowledges the device when to start showing the BCD number
  input clk;
  input reset;
  reg [3:0] bcd_2 = 4'b0;
  reg [3:0] bcd_1 = 4'b0; 
  reg [4:0] binary;

  
  parameter start   = 0;
  parameter shift_1 = 1;
  parameter check_1 = 2;
  parameter add_1   = 3;
  parameter shift_2 = 4;
  parameter check_2 = 5;
  parameter add_2   = 6;
  parameter shift_3 = 7;
  parameter check_3 = 8;
  parameter add_3   = 9; 
  parameter shift_4 = 10;
  parameter check_4 = 11;
  parameter add_4   = 12;
  parameter shift_5 = 13;
  
  reg [3:0] state;
  reg [3:0] next_state;
  


  always@(posedge clk, ~reset) begin
    if (~reset) begin
      state <= start;
      binary <= bin[4:0];
    end
    else begin 
      state <= next_state;
    end
  end
  
  always@(state) begin
    case (state) 
      start   : begin 
                bcd_1 <= {1'b0,1'b0,bin[6:5]};
                bcd_2 <= 4'b0;
                next_state <= shift_1;
                if_done <= 1'b0;
                end
      shift_1 : begin
                bcd_2 <= {bcd_2[2:0],bcd_1[3]};
                bcd_1 <= {bcd_1[2:0],binary[4]};
                binary <= {binary[3:0],1'b0};
                next_state <= check_1;
                end
      check_1 : begin
                if (bcd_1 > 4'b0100) begin
                  next_state <= add_1;
                end
                else next_state <= shift_2;
                end
      add_1   : begin
                bcd_1 <= bcd_1 + 4'b0011;
                next_state <= shift_2;
                end
      shift_2 : begin
                bcd_2 <= {bcd_2[2:0],bcd_1[3]};
                bcd_1 <= {bcd_1[2:0],binary[4]};
                binary <= {binary[3:0],1'b0};
                next_state <= check_2;
                end
      check_2 : begin
                if (bcd_1 > 4'b0100) begin
                  next_state <= add_2;
                end
                else next_state <= shift_3;
                end
      add_2   : begin
                bcd_1 <= bcd_1 + 4'b0011;
                next_state <= shift_3;
                end
      shift_3 : begin
                bcd_2 <= {bcd_2[2:0],bcd_1[3]};
                bcd_1 <= {bcd_1[2:0],binary[4]};
                binary <= {binary[3:0],1'b0};
                next_state <= check_3;
                end
      check_3 : begin
                if (bcd_1 > 4'b0100) begin
                  next_state <= add_3;
                end
                else next_state <= shift_4;
                end
      add_3   : begin
                bcd_1 <= bcd_1 + 4'b0011;
                next_state <= shift_4;
                end
      shift_4 : begin
                bcd_2 <= {bcd_2[2:0],bcd_1[3]};
                bcd_1 <= {bcd_1[2:0],binary[4]};
                binary <= {binary[3:0],1'b0};
                next_state <= check_4;
                end
      check_4 : begin
                if (bcd_1 > 4'b0100) begin
                  next_state <= add_4;
                end
                else next_state <= shift_5;
                end
      add_4   : begin
                bcd_1 <= bcd_1 + 4'b0011;
                next_state <= shift_5;
                end
      shift_5 : begin
                bcd_2 <= {bcd_2[2:0],bcd_1[3]};
                bcd_1 <= {bcd_1[2:0],binary[4]};
                binary <= {binary[3:0],1'b0};
                if_done <= 1'b1;
                end
    endcase
  end
  assign BCD1 = bcd_1;
  assign BCD2 = bcd_2;
endmodule

LM07_read.v
`include "bin2BCD.v"


//DEFINES
`define CS_LOW_COUNT    5'd12 
`define CS_HIGH_COUNT   5'd30
`define CS_initial      1'b1
`define SCK_initial     1'b1

module LM07_read(RSTN,SYSCLK,SIO,CS,disp,SCK,data);

input RSTN,SYSCLK,SIO;
output reg CS  = `CS_initial;
output reg SCK =`SCK_initial;
output [1:0] disp;
reg [7:0] data_latched;         //remove output
output [7:0] data;                     //final output

reg SEL_EN = 1'b1;                     // to choose 7 segment display
wire [3:0] display_data;
reg [3:0] count_SCK=4'd0;
reg [4:0] count=1'b1;
reg [7:0] data_out;
reg chk_state;                          //remove output
reg RSTN_BCD = 1'b1;                    //remove output
wire [3:0] displayLSB;           //remove output
wire [3:0] displayMSB;           //remove output
wire if_done;

bin2BCD b2B(data_latched[6:0],displayLSB,displayMSB,RSTN_BCD,SYSCLK,if_done);

always@(posedge SYSCLK) begin
    count <= count+1;
    if (count == `CS_LOW_COUNT) begin
        CS <= 1'b0;
        chk_state <= 1'b0;
        data_out <= 8'b0;
        count_SCK <= 4'd0;
        
    end
    else if (count == `CS_HIGH_COUNT) begin
        CS <=1'b1;
        count <= 1'b0;
        data_out <= 8'd0;
    end
    
end

always@(negedge SYSCLK , negedge RSTN) begin
    if (CS) begin
        SCK <= 1'b0;
    end
    else if (CS == 1'b0)begin
        SCK <= ~SCK;
    end
    if (SCK == 1'b1) begin
        RSTN_BCD <= 1'b1;
    end
end

always@(posedge SYSCLK) begin
    SEL_EN <= ~SEL_EN;
end

always@(posedge SCK) begin
        count_SCK <= count_SCK + 1;
        data_out    = data_out<<1;                   // to negate the 15th bit from temp sensor since our sensor counts from 00-99 with one sign bit so essentially 8 bits from which 7 bits are for temp sensor and one bit for sign
        data_out[0] = SIO;
        if (count_SCK == 4'd8) begin                 //to count the SCK for latching out the data just before the end of the last read cycle 
            chk_state <= 1'b1;
        end
end

always@(posedge chk_state) begin
    data_latched <= data_out;
    if (chk_state == 1'b1) begin
        RSTN_BCD <= 1'b0;
    end
end

always@(negedge chk_state) begin
    data_latched <= 8'd0;
end


assign disp[0] = ((if_done == 1'b1) && (SEL_EN == 1'b0) && (CS == 1'b1)) ? 1'b1 : 1'b0;
assign disp[1] = ((if_done == 1'b1) && (SEL_EN == 1'b1) && (CS == 1'b1)) ? 1'b1 : 1'b0;
assign display_data = (disp[1]== 1'b1) ? displayMSB : displayLSB;
assign data[7:4] = displayMSB;
assign data[3:0] = display_data;
endmodule

tb_LM07.v
`timescale 1ns/1ps

`include "LM07.v"

module tb();
wire CS,SCK;
wire SEL0,SEL1;
reg RSTN,SYSCLK;
wire SIO;
wire [1:0] disp;
wire [7:0] data;

LM07_read lm(RSTN,SYSCLK,SIO,CS,disp,SCK,data);
LM07 lm1(CS,SCK,SIO);

always #5 SYSCLK <= ~SYSCLK;

initial begin
    $dumpfile("dump.vcd");
    $dumpvars(1);
    RSTN = 1'b0;
    SYSCLK = 1'b0;
    #5 RSTN = 1'b1;
    #4000 $finish;
end
endmodule

dump.vcd
$date
	Tue Mar 28 22:28:56 2023
$end
$version
	Icarus Verilog
$end
$timescale
	1ps
$end
$scope module tb $end
$var wire 2 ! disp [1:0] $end
$var wire 8 " data [7:0] $end
$var wire 1 # SIO $end
$var wire 1 $ SCK $end
$var wire 1 % CS $end
$var reg 1 & RSTN $end
$var reg 1 ' SYSCLK $end
$upscope $end
$enddefinitions $end
$comment Show the parameter values. $end
$dumpall
$end
#0
$dumpvars
0'
0&
1%
0$
0#
b0 "
bx0 !
$end
#5000
b0x !
1'
1&
#10000
0'
#15000
bx0 !
1'
#20000
0'
#25000
b0x !
1'
#30000
0'
#35000
bx0 !
1'
#40000
0'
#45000
b0x !
1'
#50000
0'
#55000
bx0 !
1'
#60000
0'
#65000
b0x !
1'
#70000
0'
#75000
bx0 !
1'
#80000
0'
#85000
b0x !
1'
#90000
0'
#95000
bx0 !
1'
#100000
0'
#105000
b0x !
1'
#110000
0'
#115000
b0 !
0%
1'
#120000
1$
0'
#125000
1'
#130000
0$
0'
#135000
1'
#140000
1$
0'
#145000
1'
#150000
0$
0'
#155000
1'
#160000
1$
0'
#165000
1'
#170000
0$
0'
#175000
1'
#180000
1$
0'
#185000
1'
#190000
1#
0$
0'
#195000
1'
#200000
1$
0'
#205000
1'
#210000
0#
0$
0'
#215000
1'
#220000
1$
0'
#225000
1'
#230000
1#
0$
0'
#235000
1'
#240000
1$
0'
#245000
1'
#250000
0$
0'
#255000
1'
#260000
1$
0'
#265000
1'
#270000
0$
0'
#275000
1'
#280000
1$
0'
#285000
1'
#290000
b1 "
0#
0$
0'
#295000
1%
1'
#300000
0'
#305000
b10 "
1'
#310000
0'
#315000
1'
#320000
0'
#325000
b101 "
1'
#330000
0'
#335000
1'
#340000
0'
#345000
b1000 "
1'
#350000
0'
#355000
b10001 "
1'
#360000
0'
#365000
1'
#370000
0'
#375000
b10 !
b100010 "
1'
#380000
0'
#385000
b100011 "
b1 !
1'
#390000
0'
#395000
b100010 "
b10 !
1'
#400000
0'
#405000
b100011 "
b1 !
1'
#410000
0'
#415000
b100010 "
b10 !
1'
#420000
0'
#425000
b100011 "
b0 !
0%
1'
#430000
1$
0'
#435000
1'
#440000
0$
0'
#445000
1'
#450000
1$
0'
#455000
1'
#460000
0$
0'
#465000
1'
#470000
1$
0'
#475000
1'
#480000
0$
0'
#485000
1'
#490000
1$
0'
#495000
1'
#500000
1#
0$
0'
#505000
1'
#510000
1$
0'
#515000
1'
#520000
0#
0$
0'
#525000
1'
#530000
1$
0'
#535000
1'
#540000
1#
0$
0'
#545000
1'
#550000
1$
0'
#555000
1'
#560000
0$
0'
#565000
1'
#570000
1$
0'
#575000
1'
#580000
0$
0'
#585000
1'
#590000
b0 "
1$
0'
#595000
1'
#600000
b1 "
0#
0$
0'
#605000
1%
1'
#610000
0'
#615000
b10 "
1'
#620000
0'
#625000
1'
#630000
0'
#635000
b101 "
1'
#640000
0'
#645000
1'
#650000
0'
#655000
b1000 "
1'
#660000
0'
#665000
b10001 "
1'
#670000
0'
#675000
1'
#680000
0'
#685000
b1 !
b100011 "
1'
#690000
0'
#695000
b100010 "
b10 !
1'
#700000
0'
#705000
b100011 "
b1 !
1'
#710000
0'
#715000
b100010 "
b10 !
1'
#720000
0'
#725000
b100011 "
b1 !
1'
#730000
0'
#735000
b0 !
0%
1'
#740000
1$
0'
#745000
1'
#750000
0$
0'
#755000
1'
#760000
1$
0'
#765000
1'
#770000
0$
0'
#775000
1'
#780000
1$
0'
#785000
1'
#790000
0$
0'
#795000
1'
#800000
1$
0'
#805000
1'
#810000
1#
0$
0'
#815000
1'
#820000
1$
0'
#825000
1'
#830000
0#
0$
0'
#835000
1'
#840000
1$
0'
#845000
1'
#850000
1#
0$
0'
#855000
1'
#860000
1$
0'
#865000
1'
#870000
0$
0'
#875000
1'
#880000
1$
0'
#885000
1'
#890000
0$
0'
#895000
1'
#900000
b0 "
1$
0'
#905000
1'
#910000
b1 "
0#
0$
0'
#915000
1%
1'
#920000
0'
#925000
b10 "
1'
#930000
0'
#935000
1'
#940000
0'
#945000
b101 "
1'
#950000
0'
#955000
1'
#960000
0'
#965000
b1000 "
1'
#970000
0'
#975000
b10001 "
1'
#980000
0'
#985000
1'
#990000
0'
#995000
b10 !
b100010 "
1'
#1000000
0'
#1005000
b100011 "
b1 !
1'
#1010000
0'
#1015000
b100010 "
b10 !
1'
#1020000
0'
#1025000
b100011 "
b1 !
1'
#1030000
0'
#1035000
b100010 "
b10 !
1'
#1040000
0'
#1045000
b100011 "
b0 !
0%
1'
#1050000
1$
0'
#1055000
1'
#1060000
0$
0'
#1065000
1'
#1070000
1$
0'
#1075000
1'
#1080000
0$
0'
#1085000
1'
#1090000
1$
0'
#1095000
1'
#1100000
0$
0'
#1105000
1'
#1110000
1$
0'
#1115000
1'
#1120000
1#
0$
0'
#1125000
1'
#1130000
1$
0'
#1135000
1'
#1140000
0#
0$
0'
#1145000
1'
#1150000
1$
0'
#1155000
1'
#1160000
1#
0$
0'
#1165000
1'
#1170000
1$
0'
#1175000
1'
#1180000
0$
0'
#1185000
1'
#1190000
1$
0'
#1195000
1'
#1200000
0$
0'
#1205000
1'
#1210000
b0 "
1$
0'
#1215000
1'
#1220000
b1 "
0#
0$
0'
#1225000
1%
1'
#1230000
0'
#1235000
b10 "
1'
#1240000
0'
#1245000
1'
#1250000
0'
#1255000
b101 "
1'
#1260000
0'
#1265000
1'
#1270000
0'
#1275000
b1000 "
1'
#1280000
0'
#1285000
b10001 "
1'
#1290000
0'
#1295000
1'
#1300000
0'
#1305000
b1 !
b100011 "
1'
#1310000
0'
#1315000
b100010 "
b10 !
1'
#1320000
0'
#1325000
b100011 "
b1 !
1'
#1330000
0'
#1335000
b100010 "
b10 !
1'
#1340000
0'
#1345000
b100011 "
b1 !
1'
#1350000
0'
#1355000
b0 !
0%
1'
#1360000
1$
0'
#1365000
1'
#1370000
0$
0'
#1375000
1'
#1380000
1$
0'
#1385000
1'
#1390000
0$
0'
#1395000
1'
#1400000
1$
0'
#1405000
1'
#1410000
0$
0'
#1415000
1'
#1420000
1$
0'
#1425000
1'
#1430000
1#
0$
0'
#1435000
1'
#1440000
1$
0'
#1445000
1'
#1450000
0#
0$
0'
#1455000
1'
#1460000
1$
0'
#1465000
1'
#1470000
1#
0$
0'
#1475000
1'
#1480000
1$
0'
#1485000
1'
#1490000
0$
0'
#1495000
1'
#1500000
1$
0'
#1505000
1'
#1510000
0$
0'
#1515000
1'
#1520000
b0 "
1$
0'
#1525000
1'
#1530000
b1 "
0#
0$
0'
#1535000
1%
1'
#1540000
0'
#1545000
b10 "
1'
#1550000
0'
#1555000
1'
#1560000
0'
#1565000
b101 "
1'
#1570000
0'
#1575000
1'
#1580000
0'
#1585000
b1000 "
1'
#1590000
0'
#1595000
b10001 "
1'
#1600000
0'
#1605000
1'
#1610000
0'
#1615000
b10 !
b100010 "
1'
#1620000
0'
#1625000
b100011 "
b1 !
1'
#1630000
0'
#1635000
b100010 "
b10 !
1'
#1640000
0'
#1645000
b100011 "
b1 !
1'
#1650000
0'
#1655000
b100010 "
b10 !
1'
#1660000
0'
#1665000
b100011 "
b0 !
0%
1'
#1670000
1$
0'
#1675000
1'
#1680000
0$
0'
#1685000
1'
#1690000
1$
0'
#1695000
1'
#1700000
0$
0'
#1705000
1'
#1710000
1$
0'
#1715000
1'
#1720000
0$
0'
#1725000
1'
#1730000
1$
0'
#1735000
1'
#1740000
1#
0$
0'
#1745000
1'
#1750000
1$
0'
#1755000
1'
#1760000
0#
0$
0'
#1765000
1'
#1770000
1$
0'
#1775000
1'
#1780000
1#
0$
0'
#1785000
1'
#1790000
1$
0'
#1795000
1'
#1800000
0$
0'
#1805000
1'
#1810000
1$
0'
#1815000
1'
#1820000
0$
0'
#1825000
1'
#1830000
b0 "
1$
0'
#1835000
1'
#1840000
b1 "
0#
0$
0'
#1845000
1%
1'
#1850000
0'
#1855000
b10 "
1'
#1860000
0'
#1865000
1'
#1870000
0'
#1875000
b101 "
1'
#1880000
0'
#1885000
1'
#1890000
0'
#1895000
b1000 "
1'
#1900000
0'
#1905000
b10001 "
1'
#1910000
0'
#1915000
1'
#1920000
0'
#1925000
b1 !
b100011 "
1'
#1930000
0'
#1935000
b100010 "
b10 !
1'
#1940000
0'
#1945000
b100011 "
b1 !
1'
#1950000
0'
#1955000
b100010 "
b10 !
1'
#1960000
0'
#1965000
b100011 "
b1 !
1'
#1970000
0'
#1975000
b0 !
0%
1'
#1980000
1$
0'
#1985000
1'
#1990000
0$
0'
#1995000
1'
#2000000
1$
0'
#2005000
1'
#2010000
0$
0'
#2015000
1'
#2020000
1$
0'
#2025000
1'
#2030000
0$
0'
#2035000
1'
#2040000
1$
0'
#2045000
1'
#2050000
1#
0$
0'
#2055000
1'
#2060000
1$
0'
#2065000
1'
#2070000
0#
0$
0'
#2075000
1'
#2080000
1$
0'
#2085000
1'
#2090000
1#
0$
0'
#2095000
1'
#2100000
1$
0'
#2105000
1'
#2110000
0$
0'
#2115000
1'
#2120000
1$
0'
#2125000
1'
#2130000
0$
0'
#2135000
1'
#2140000
b0 "
1$
0'
#2145000
1'
#2150000
b1 "
0#
0$
0'
#2155000
1%
1'
#2160000
0'
#2165000
b10 "
1'
#2170000
0'
#2175000
1'
#2180000
0'
#2185000
b101 "
1'
#2190000
0'
#2195000
1'
#2200000
0'
#2205000
b1000 "
1'
#2210000
0'
#2215000
b10001 "
1'
#2220000
0'
#2225000
1'
#2230000
0'
#2235000
b10 !
b100010 "
1'
#2240000
0'
#2245000
b100011 "
b1 !
1'
#2250000
0'
#2255000
b100010 "
b10 !
1'
#2260000
0'
#2265000
b100011 "
b1 !
1'
#2270000
0'
#2275000
b100010 "
b10 !
1'
#2280000
0'
#2285000
b100011 "
b0 !
0%
1'
#2290000
1$
0'
#2295000
1'
#2300000
0$
0'
#2305000
1'
#2310000
1$
0'
#2315000
1'
#2320000
0$
0'
#2325000
1'
#2330000
1$
0'
#2335000
1'
#2340000
0$
0'
#2345000
1'
#2350000
1$
0'
#2355000
1'
#2360000
1#
0$
0'
#2365000
1'
#2370000
1$
0'
#2375000
1'
#2380000
0#
0$
0'
#2385000
1'
#2390000
1$
0'
#2395000
1'
#2400000
1#
0$
0'
#2405000
1'
#2410000
1$
0'
#2415000
1'
#2420000
0$
0'
#2425000
1'
#2430000
1$
0'
#2435000
1'
#2440000
0$
0'
#2445000
1'
#2450000
b0 "
1$
0'
#2455000
1'
#2460000
b1 "
0#
0$
0'
#2465000
1%
1'
#2470000
0'
#2475000
b10 "
1'
#2480000
0'
#2485000
1'
#2490000
0'
#2495000
b101 "
1'
#2500000
0'
#2505000
1'
#2510000
0'
#2515000
b1000 "
1'
#2520000
0'
#2525000
b10001 "
1'
#2530000
0'
#2535000
1'
#2540000
0'
#2545000
b1 !
b100011 "
1'
#2550000
0'
#2555000
b100010 "
b10 !
1'
#2560000
0'
#2565000
b100011 "
b1 !
1'
#2570000
0'
#2575000
b100010 "
b10 !
1'
#2580000
0'
#2585000
b100011 "
b1 !
1'
#2590000
0'
#2595000
b0 !
0%
1'
#2600000
1$
0'
#2605000
1'
#2610000
0$
0'
#2615000
1'
#2620000
1$
0'
#2625000
1'
#2630000
0$
0'
#2635000
1'
#2640000
1$
0'
#2645000
1'
#2650000
0$
0'
#2655000
1'
#2660000
1$
0'
#2665000
1'
#2670000
1#
0$
0'
#2675000
1'
#2680000
1$
0'
#2685000
1'
#2690000
0#
0$
0'
#2695000
1'
#2700000
1$
0'
#2705000
1'
#2710000
1#
0$
0'
#2715000
1'
#2720000
1$
0'
#2725000
1'
#2730000
0$
0'
#2735000
1'
#2740000
1$
0'
#2745000
1'
#2750000
0$
0'
#2755000
1'
#2760000
b0 "
1$
0'
#2765000
1'
#2770000
b1 "
0#
0$
0'
#2775000
1%
1'
#2780000
0'
#2785000
b10 "
1'
#2790000
0'
#2795000
1'
#2800000
0'
#2805000
b101 "
1'
#2810000
0'
#2815000
1'
#2820000
0'
#2825000
b1000 "
1'
#2830000
0'
#2835000
b10001 "
1'
#2840000
0'
#2845000
1'
#2850000
0'
#2855000
b10 !
b100010 "
1'
#2860000
0'
#2865000
b100011 "
b1 !
1'
#2870000
0'
#2875000
b100010 "
b10 !
1'
#2880000
0'
#2885000
b100011 "
b1 !
1'
#2890000
0'
#2895000
b100010 "
b10 !
1'
#2900000
0'
#2905000
b100011 "
b0 !
0%
1'
#2910000
1$
0'
#2915000
1'
#2920000
0$
0'
#2925000
1'
#2930000
1$
0'
#2935000
1'
#2940000
0$
0'
#2945000
1'
#2950000
1$
0'
#2955000
1'
#2960000
0$
0'
#2965000
1'
#2970000
1$
0'
#2975000
1'
#2980000
1#
0$
0'
#2985000
1'
#2990000
1$
0'
#2995000
1'
#3000000
0#
0$
0'
#3005000
1'
#3010000
1$
0'
#3015000
1'
#3020000
1#
0$
0'
#3025000
1'
#3030000
1$
0'
#3035000
1'
#3040000
0$
0'
#3045000
1'
#3050000
1$
0'
#3055000
1'
#3060000
0$
0'
#3065000
1'
#3070000
b0 "
1$
0'
#3075000
1'
#3080000
b1 "
0#
0$
0'
#3085000
1%
1'
#3090000
0'
#3095000
b10 "
1'
#3100000
0'
#3105000
1'
#3110000
0'
#3115000
b101 "
1'
#3120000
0'
#3125000
1'
#3130000
0'
#3135000
b1000 "
1'
#3140000
0'
#3145000
b10001 "
1'
#3150000
0'
#3155000
1'
#3160000
0'
#3165000
b1 !
b100011 "
1'
#3170000
0'
#3175000
b100010 "
b10 !
1'
#3180000
0'
#3185000
b100011 "
b1 !
1'
#3190000
0'
#3195000
b100010 "
b10 !
1'
#3200000
0'
#3205000
b100011 "
b1 !
1'
#3210000
0'
#3215000
b0 !
0%
1'
#3220000
1$
0'
#3225000
1'
#3230000
0$
0'
#3235000
1'
#3240000
1$
0'
#3245000
1'
#3250000
0$
0'
#3255000
1'
#3260000
1$
0'
#3265000
1'
#3270000
0$
0'
#3275000
1'
#3280000
1$
0'
#3285000
1'
#3290000
1#
0$
0'
#3295000
1'
#3300000
1$
0'
#3305000
1'
#3310000
0#
0$
0'
#3315000
1'
#3320000
1$
0'
#3325000
1'
#3330000
1#
0$
0'
#3335000
1'
#3340000
1$
0'
#3345000
1'
#3350000
0$
0'
#3355000
1'
#3360000
1$
0'
#3365000
1'
#3370000
0$
0'
#3375000
1'
#3380000
b0 "
1$
0'
#3385000
1'
#3390000
b1 "
0#
0$
0'
#3395000
1%
1'
#3400000
0'
#3405000
b10 "
1'
#3410000
0'
#3415000
1'
#3420000
0'
#3425000
b101 "
1'
#3430000
0'
#3435000
1'
#3440000
0'
#3445000
b1000 "
1'
#3450000
0'
#3455000
b10001 "
1'
#3460000
0'
#3465000
1'
#3470000
0'
#3475000
b10 !
b100010 "
1'
#3480000
0'
#3485000
b100011 "
b1 !
1'
#3490000
0'
#3495000
b100010 "
b10 !
1'
#3500000
0'
#3505000
b100011 "
b1 !
1'
#3510000
0'
#3515000
b100010 "
b10 !
1'
#3520000
0'
#3525000
b100011 "
b0 !
0%
1'
#3530000
1$
0'
#3535000
1'
#3540000
0$
0'
#3545000
1'
#3550000
1$
0'
#3555000
1'
#3560000
0$
0'
#3565000
1'
#3570000
1$
0'
#3575000
1'
#3580000
0$
0'
#3585000
1'
#3590000
1$
0'
#3595000
1'
#3600000
1#
0$
0'
#3605000
1'
#3610000
1$
0'
#3615000
1'
#3620000
0#
0$
0'
#3625000
1'
#3630000
1$
0'
#3635000
1'
#3640000
1#
0$
0'
#3645000
1'
#3650000
1$
0'
#3655000
1'
#3660000
0$
0'
#3665000
1'
#3670000
1$
0'
#3675000
1'
#3680000
0$
0'
#3685000
1'
#3690000
b0 "
1$
0'
#3695000
1'
#3700000
b1 "
0#
0$
0'
#3705000
1%
1'
#3710000
0'
#3715000
b10 "
1'
#3720000
0'
#3725000
1'
#3730000
0'
#3735000
b101 "
1'
#3740000
0'
#3745000
1'
#3750000
0'
#3755000
b1000 "
1'
#3760000
0'
#3765000
b10001 "
1'
#3770000
0'
#3775000
1'
#3780000
0'
#3785000
b1 !
b100011 "
1'
#3790000
0'
#3795000
b100010 "
b10 !
1'
#3800000
0'
#3805000
b100011 "
b1 !
1'
#3810000
0'
#3815000
b100010 "
b10 !
1'
#3820000
0'
#3825000
b100011 "
b1 !
1'
#3830000
0'
#3835000
b0 !
0%
1'
#3840000
1$
0'
#3845000
1'
#3850000
0$
0'
#3855000
1'
#3860000
1$
0'
#3865000
1'
#3870000
0$
0'
#3875000
1'
#3880000
1$
0'
#3885000
1'
#3890000
0$
0'
#3895000
1'
#3900000
1$
0'
#3905000
1'
#3910000
1#
0$
0'
#3915000
1'
#3920000
1$
0'
#3925000
1'
#3930000
0#
0$
0'
#3935000
1'
#3940000
1$
0'
#3945000
1'
#3950000
1#
0$
0'
#3955000
1'
#3960000
1$
0'
#3965000
1'
#3970000
0$
0'
#3975000
1'
#3980000
1$
0'
#3985000
1'
#3990000
0$
0'
#3995000
1'
#4000000
b0 "
1$
0'
