LM07.v
//Define
`define TEMP_SET  16'h3100

module LM07(CS, SCK, SIO);
  output SIO;
  input SCK, CS;

  reg [15:0] shift_reg;
  wire clk_gated;

  initial begin
    shift_reg = `TEMP_SET; 
  end
  
  assign SIO = shift_reg[15];

  assign clk_gated = ~CS & SCK;

  always @(CS)
   begin
     shift_reg = `TEMP_SET;
   end

  always @(negedge clk_gated)
    begin
      shift_reg = shift_reg<<1;
    end
endmodule

bin2BCD.v
module bin2BCD(bin,BCD1,BCD2,reset,clk);
  input  [6:0] bin;
  output [3:0] BCD1;
  output [3:0] BCD2;
  input clk;
  input reset;
  reg [3:0] bcd_2 = 4'b0;
  reg [3:0] bcd_1 = 4'b0; 
  reg [4:0] binary;
  
  parameter start   = 0;
  parameter shift_1 = 1;
  parameter check_1 = 2;
  parameter add_1   = 3;
  parameter shift_2 = 4;
  parameter check_2 = 5;
  parameter add_2   = 6;
  parameter shift_3 = 7;
  parameter check_3 = 8;
  parameter add_3   = 9; 
  parameter shift_4 = 10;
  parameter check_4 = 11;
  parameter add_4   = 12;
  parameter shift_5 = 13;
  
  reg [3:0] state;
  reg [3:0] next_state;
  


  always@(posedge clk, ~reset) begin
    if (~reset) begin
      state <= start;
      binary <= bin[4:0];
    end
    else begin 
      state <= next_state;
    end
  end
  
  always@(state) begin
    case (state) 
      start   : begin 
                bcd_1 <= {1'b0,1'b0,bin[6:5]};
                bcd_2 <= 4'b0;
                next_state <= shift_1;
                end
      shift_1 : begin
                bcd_2 <= {bcd_2[2:0],bcd_1[3]};
                bcd_1 <= {bcd_1[2:0],binary[4]};
                binary <= {binary[3:0],1'b0};
                next_state <= check_1;
                end
      check_1 : begin
                if (bcd_1 > 4'b0100) begin
                  next_state <= add_1;
                end
                else next_state <= shift_2;
                end
      add_1   : begin
                bcd_1 <= bcd_1 + 4'b0011;
                next_state <= shift_2;
                end
      shift_2 : begin
                bcd_2 <= {bcd_2[2:0],bcd_1[3]};
                bcd_1 <= {bcd_1[2:0],binary[4]};
                binary <= {binary[3:0],1'b0};
                next_state <= check_2;
                end
      check_2 : begin
                if (bcd_1 > 4'b0100) begin
                  next_state <= add_2;
                end
                else next_state <= shift_3;
                end
      add_2   : begin
                bcd_1 <= bcd_1 + 4'b0011;
                next_state <= shift_3;
                end
      shift_3 : begin
                bcd_2 <= {bcd_2[2:0],bcd_1[3]};
                bcd_1 <= {bcd_1[2:0],binary[4]};
                binary <= {binary[3:0],1'b0};
                next_state <= check_3;
                end
      check_3 : begin
                if (bcd_1 > 4'b0100) begin
                  next_state <= add_3;
                end
                else next_state <= shift_4;
                end
      add_3   : begin
                bcd_1 <= bcd_1 + 4'b0011;
                next_state <= shift_4;
                end
      shift_4 : begin
                bcd_2 <= {bcd_2[2:0],bcd_1[3]};
                bcd_1 <= {bcd_1[2:0],binary[4]};
                binary <= {binary[3:0],1'b0};
                next_state <= check_4;
                end
      check_4 : begin
                if (bcd_1 > 4'b0100) begin
                  next_state <= add_4;
                end
                else next_state <= shift_5;
                end
      add_4   : begin
                bcd_1 <= bcd_1 + 4'b0011;
                next_state <= shift_5;
                end
      shift_5 : begin
                bcd_2 <= {bcd_2[2:0],bcd_1[3]};
                bcd_1 <= {bcd_1[2:0],binary[4]};
                binary <= {binary[3:0],1'b0};
                end
    endcase
  end
  assign BCD1 = bcd_1;
  assign BCD2 = bcd_2;
endmodule

LM07_read.v
`include "bin2BCD.v"


//DEFINES
`define CS_LOW_COUNT    5'd10 
`define CS_HIGH_COUNT   5'd28
`define CS_initial      1'b1;
`define SCK_initial     1'b1;

module LM07_read(RSTN,SYSCLK,SIO,CS,SEL0,SEL1,SCK,data_latched);

input RSTN,SYSCLK,SIO;
output reg CS  = `CS_initial;
output reg SCK =`SCK_initial;
output SEL0;
output SEL1;
output reg [7:0] data_latched;

reg [3:0] count_SCK=4'd0;
reg [4:0] count=1'b1;
reg [7:0] data_out;
reg chk_state;                   //remove output
reg RSTN_BCD = 1'b1;             //remove output
wire [3:0] displayLSB;           //remove output
wire [3:0] displayMSB;           //remove output

bin2BCD b2B(data_latched[6:0],displayLSB,displayMSB,RSTN_BCD,SYSCLK);

always@(posedge SYSCLK) begin
    count <= count+1;
    if (count == `CS_LOW_COUNT) begin
        CS <= 1'b0;
        chk_state <= 1'b0;
        data_out <= 8'b0;
        count_SCK <= 4'd0;
        
    end
    else if (count == `CS_HIGH_COUNT) begin
        CS <=1'b1;
        count <= 1'b0;
        data_out <= 8'd0;
    end
    
end

always@(negedge SYSCLK , negedge RSTN) begin
    if (CS) begin
        SCK <= 1'b0;
    end
    else if (CS == 1'b0)begin
        SCK <= ~SCK;
    end
    if (SCK == 1'b1) begin
        RSTN_BCD <= 1'b1;
    end
end

always@(posedge SCK) begin
        count_SCK <= count_SCK + 1;
        data_out    = data_out<<1;                   // to negate the 15th bit from temp sensor since our sensor counts from 00-99 with one sign bit so essentially 8 bits from which 7 bits are for temp sensor and one bit for sign
        data_out[0] = SIO;
        if (count_SCK == 4'd8) begin                 //to count the SCK for latching out the data just before the end of the last read cycle 
            chk_state <= 1'b1;
        end
end

always@(posedge chk_state) begin
    data_latched <= data_out;
    if (chk_state == 1'b1) begin
        RSTN_BCD <= 1'b0;
    end
end

always@(negedge chk_state) begin
    data_latched <= 8'd0;
end

endmodule

tb_LM07.v
`timescale 1ns/1ps

`include "LM07.v"

module tb();
wire CS,SCK;
wire SEL0,SEL1;
reg RSTN,SYSCLK;
wire SIO;
wire [7:0] data_latched;


LM07_read lm(RSTN,SYSCLK,SIO,CS,SEL0,SEL1,SCK,data_latched);
LM07 lm1(CS,SCK,SIO);

always #5 SYSCLK <= ~SYSCLK;

initial begin
    $dumpfile("dump.vcd");
    $dumpvars(1);
    RSTN = 1'b0;
    SYSCLK = 1'b0;
    #5 RSTN = 1'b1;
    #2000 $finish;
end
endmodule

dump.vcd
$date
	Sun Mar 26 10:43:11 2023
$end
$version
	Icarus Verilog
$end
$timescale
	1ps
$end
$scope module tb $end
$var wire 1 ! SEL0 $end
$var wire 1 " SEL1 $end
$var wire 8 # data_latched [7:0] $end
$var wire 1 $ SIO $end
$var wire 1 % SCK $end
$var wire 1 & CS $end
$var reg 1 ' RSTN $end
$var reg 1 ( SYSCLK $end
$upscope $end
$enddefinitions $end
$comment Show the parameter values. $end
$dumpall
$end
#0
$dumpvars
0(
0'
1&
0%
0$
bx #
z"
z!
$end
#5000
1(
1'
#10000
0(
#15000
1(
#20000
0(
#25000
1(
#30000
0(
#35000
1(
#40000
0(
#45000
1(
#50000
0(
#55000
1(
#60000
0(
#65000
1(
#70000
0(
#75000
1(
#80000
0(
#85000
1(
#90000
0(
#95000
b0 #
0&
1(
#100000
1%
0(
#105000
1(
#110000
0%
0(
#115000
1(
#120000
1%
0(
#125000
1(
#130000
1$
0%
0(
#135000
1(
#140000
1%
0(
#145000
1(
#150000
0%
0(
#155000
1(
#160000
1%
0(
#165000
1(
#170000
0$
0%
0(
#175000
1(
#180000
1%
0(
#185000
1(
#190000
0%
0(
#195000
1(
#200000
1%
0(
#205000
1(
#210000
0%
0(
#215000
1(
#220000
1%
0(
#225000
1(
#230000
1$
0%
0(
#235000
1(
#240000
1%
0(
#245000
1(
#250000
0$
0%
0(
#255000
1(
#260000
b1100010 #
1%
0(
#265000
1(
#270000
0%
0(
#275000
1&
1(
#280000
0(
#285000
1(
#290000
0(
#295000
1(
#300000
0(
#305000
1(
#310000
0(
#315000
1(
#320000
0(
#325000
1(
#330000
0(
#335000
1(
#340000
0(
#345000
1(
#350000
0(
#355000
1(
#360000
0(
#365000
1(
#370000
0(
#375000
1(
#380000
0(
#385000
b0 #
0&
1(
#390000
1%
0(
#395000
1(
#400000
0%
0(
#405000
1(
#410000
1%
0(
#415000
1(
#420000
1$
0%
0(
#425000
1(
#430000
1%
0(
#435000
1(
#440000
0%
0(
#445000
1(
#450000
1%
0(
#455000
1(
#460000
0$
0%
0(
#465000
1(
#470000
1%
0(
#475000
1(
#480000
0%
0(
#485000
1(
#490000
1%
0(
#495000
1(
#500000
0%
0(
#505000
1(
#510000
1%
0(
#515000
1(
#520000
1$
0%
0(
#525000
1(
#530000
1%
0(
#535000
1(
#540000
0$
0%
0(
#545000
1(
#550000
b1100010 #
1%
0(
#555000
1(
#560000
0%
0(
#565000
1&
1(
#570000
0(
#575000
1(
#580000
0(
#585000
1(
#590000
0(
#595000
1(
#600000
0(
#605000
1(
#610000
0(
#615000
1(
#620000
0(
#625000
1(
#630000
0(
#635000
1(
#640000
0(
#645000
1(
#650000
0(
#655000
1(
#660000
0(
#665000
1(
#670000
0(
#675000
b0 #
0&
1(
#680000
1%
0(
#685000
1(
#690000
0%
0(
#695000
1(
#700000
1%
0(
#705000
1(
#710000
1$
0%
0(
#715000
1(
#720000
1%
0(
#725000
1(
#730000
0%
0(
#735000
1(
#740000
1%
0(
#745000
1(
#750000
0$
0%
0(
#755000
1(
#760000
1%
0(
#765000
1(
#770000
0%
0(
#775000
1(
#780000
1%
0(
#785000
1(
#790000
0%
0(
#795000
1(
#800000
1%
0(
#805000
1(
#810000
1$
0%
0(
#815000
1(
#820000
1%
0(
#825000
1(
#830000
0$
0%
0(
#835000
1(
#840000
b1100010 #
1%
0(
#845000
1(
#850000
0%
0(
#855000
1&
1(
#860000
0(
#865000
1(
#870000
0(
#875000
1(
#880000
0(
#885000
1(
#890000
0(
#895000
1(
#900000
0(
#905000
1(
#910000
0(
#915000
1(
#920000
0(
#925000
1(
#930000
0(
#935000
1(
#940000
0(
#945000
1(
#950000
0(
#955000
1(
#960000
0(
#965000
b0 #
0&
1(
#970000
1%
0(
#975000
1(
#980000
0%
0(
#985000
1(
#990000
1%
0(
#995000
1(
#1000000
1$
0%
0(
#1005000
1(
#1010000
1%
0(
#1015000
1(
#1020000
0%
0(
#1025000
1(
#1030000
1%
0(
#1035000
1(
#1040000
0$
0%
0(
#1045000
1(
#1050000
1%
0(
#1055000
1(
#1060000
0%
0(
#1065000
1(
#1070000
1%
0(
#1075000
1(
#1080000
0%
0(
#1085000
1(
#1090000
1%
0(
#1095000
1(
#1100000
1$
0%
0(
#1105000
1(
#1110000
1%
0(
#1115000
1(
#1120000
0$
0%
0(
#1125000
1(
#1130000
b1100010 #
1%
0(
#1135000
1(
#1140000
0%
0(
#1145000
1&
1(
#1150000
0(
#1155000
1(
#1160000
0(
#1165000
1(
#1170000
0(
#1175000
1(
#1180000
0(
#1185000
1(
#1190000
0(
#1195000
1(
#1200000
0(
#1205000
1(
#1210000
0(
#1215000
1(
#1220000
0(
#1225000
1(
#1230000
0(
#1235000
1(
#1240000
0(
#1245000
1(
#1250000
0(
#1255000
b0 #
0&
1(
#1260000
1%
0(
#1265000
1(
#1270000
0%
0(
#1275000
1(
#1280000
1%
0(
#1285000
1(
#1290000
1$
0%
0(
#1295000
1(
#1300000
1%
0(
#1305000
1(
#1310000
0%
0(
#1315000
1(
#1320000
1%
0(
#1325000
1(
#1330000
0$
0%
0(
#1335000
1(
#1340000
1%
0(
#1345000
1(
#1350000
0%
0(
#1355000
1(
#1360000
1%
0(
#1365000
1(
#1370000
0%
0(
#1375000
1(
#1380000
1%
0(
#1385000
1(
#1390000
1$
0%
0(
#1395000
1(
#1400000
1%
0(
#1405000
1(
#1410000
0$
0%
0(
#1415000
1(
#1420000
b1100010 #
1%
0(
#1425000
1(
#1430000
0%
0(
#1435000
1&
1(
#1440000
0(
#1445000
1(
#1450000
0(
#1455000
1(
#1460000
0(
#1465000
1(
#1470000
0(
#1475000
1(
#1480000
0(
#1485000
1(
#1490000
0(
#1495000
1(
#1500000
0(
#1505000
1(
#1510000
0(
#1515000
1(
#1520000
0(
#1525000
1(
#1530000
0(
#1535000
1(
#1540000
0(
#1545000
b0 #
0&
1(
#1550000
1%
0(
#1555000
1(
#1560000
0%
0(
#1565000
1(
#1570000
1%
0(
#1575000
1(
#1580000
1$
0%
0(
#1585000
1(
#1590000
1%
0(
#1595000
1(
#1600000
0%
0(
#1605000
1(
#1610000
1%
0(
#1615000
1(
#1620000
0$
0%
0(
#1625000
1(
#1630000
1%
0(
#1635000
1(
#1640000
0%
0(
#1645000
1(
#1650000
1%
0(
#1655000
1(
#1660000
0%
0(
#1665000
1(
#1670000
1%
0(
#1675000
1(
#1680000
1$
0%
0(
#1685000
1(
#1690000
1%
0(
#1695000
1(
#1700000
0$
0%
0(
#1705000
1(
#1710000
b1100010 #
1%
0(
#1715000
1(
#1720000
0%
0(
#1725000
1&
1(
#1730000
0(
#1735000
1(
#1740000
0(
#1745000
1(
#1750000
0(
#1755000
1(
#1760000
0(
#1765000
1(
#1770000
0(
#1775000
1(
#1780000
0(
#1785000
1(
#1790000
0(
#1795000
1(
#1800000
0(
#1805000
1(
#1810000
0(
#1815000
1(
#1820000
0(
#1825000
1(
#1830000
0(
#1835000
b0 #
0&
1(
#1840000
1%
0(
#1845000
1(
#1850000
0%
0(
#1855000
1(
#1860000
1%
0(
#1865000
1(
#1870000
1$
0%
0(
#1875000
1(
#1880000
1%
0(
#1885000
1(
#1890000
0%
0(
#1895000
1(
#1900000
1%
0(
#1905000
1(
#1910000
0$
0%
0(
#1915000
1(
#1920000
1%
0(
#1925000
1(
#1930000
0%
0(
#1935000
1(
#1940000
1%
0(
#1945000
1(
#1950000
0%
0(
#1955000
1(
#1960000
1%
0(
#1965000
1(
#1970000
1$
0%
0(
#1975000
1(
#1980000
1%
0(
#1985000
1(
#1990000
0$
0%
0(
#1995000
1(
#2000000
b1100010 #
1%
0(
