LM70.v
//Define
`define TEMP_SET  16'h44C0

module LM07(CS, SCK, SIO);
  output SIO;
  input SCK, CS;

  reg [15:0] shift_reg;
  wire clk_gated;

  initial begin
    shift_reg = `TEMP_SET; 
  end
  
  assign SIO = shift_reg[15];

  assign clk_gated = ~CS & SCK;

  always @(CS)
   begin
     shift_reg = `TEMP_SET;
   end

  always @(negedge clk_gated)
    begin
      shift_reg = shift_reg<<1;
    end
endmodule

LM07_read.v
//DEFINES
`define RST_COUNT       5'b00000
`define MAX_COUNT       5'b11100
`define SPI_IDLE	    1'b0
`define SPI_READ	    1'b1
`define CS_LOW_COUNT    5'd4
`define CS_HIGH_COUNT   5'd20

module LM07_read(RSTN,SYSCLK,SIO,CS,SEL0,SEL1,SCK);

input RSTN,SYSCLK,SIO;
output reg CS = 1'b1;
output reg SCK =1'b1;;
output SEL0;
output SEL1;
reg [4:0] count=1'b1;


always@(posedge SYSCLK) begin
    count <= count+1;
    if (count == 3'd4) begin
        CS <= 1'b0;
    end
    else if (count == 5'd22) begin
        CS <=1'b1;
        count <= 1'b0;
    end
end

always@(negedge SYSCLK , negedge RSTN) begin
    if (CS) begin
        SCK <= 1'b0;
    end
    else if (CS == 1'b0)begin
        SCK <= ~SCK;
    end
end


endmodule

tb_LM07.v
`timescale 1ns/1ps

`include "LM70.v"

module tb();
wire CS,SCK;
wire SEL0,SEL1;
reg RSTN,SYSCLK;
wire SIO;

LM07_read lm(RSTN,SYSCLK,SIO,CS,SEL0,SEL1,SCK);
LM07 lm1(CS,SCK,SIO);

always #5 SYSCLK <= ~SYSCLK;

initial begin
    $dumpfile("dump.vcd");
    $dumpvars(1);
    RSTN = 1'b0;
    SYSCLK = 1'b0;
    #5 RSTN = 1'b1;
    #800 $finish;
end
endmodule

dump.vcd
$date
	Sat Mar 25 14:32:12 2023
$end
$version
	Icarus Verilog
$end
$timescale
	1ps
$end
$scope module tb $end
$var wire 1 ! SEL0 $end
$var wire 1 " SEL1 $end
$var wire 1 # SIO $end
$var wire 1 $ SCK $end
$var wire 1 % CS $end
$var reg 1 & RSTN $end
$var reg 1 ' SYSCLK $end
$upscope $end
$enddefinitions $end
$comment Show the parameter values. $end
$dumpall
$end
#0
$dumpvars
0'
0&
1%
0$
1#
z"
z!
$end
#5000
1'
1&
#10000
0'
#15000
1'
#20000
0'
#25000
1'
#30000
0'
#35000
0#
0%
1'
#40000
1$
0'
#45000
1'
#50000
1#
0$
0'
#55000
1'
#60000
1$
0'
#65000
1'
#70000
0#
0$
0'
#75000
1'
#80000
1$
0'
#85000
1'
#90000
0$
0'
#95000
1'
#100000
1$
0'
#105000
1'
#110000
0$
0'
#115000
1'
#120000
1$
0'
#125000
1'
#130000
1#
0$
0'
#135000
1'
#140000
1$
0'
#145000
1'
#150000
0#
0$
0'
#155000
1'
#160000
1$
0'
#165000
1'
#170000
0$
0'
#175000
1'
#180000
1$
0'
#185000
1'
#190000
1#
0$
0'
#195000
1'
#200000
1$
0'
#205000
1'
#210000
0$
0'
#215000
0#
1%
1'
#220000
0'
#225000
1'
#230000
0'
#235000
1'
#240000
0'
#245000
1'
#250000
0'
#255000
1'
#260000
0'
#265000
0%
1'
#270000
1$
0'
#275000
1'
#280000
1#
0$
0'
#285000
1'
#290000
1$
0'
#295000
1'
#300000
0#
0$
0'
#305000
1'
#310000
1$
0'
#315000
1'
#320000
0$
0'
#325000
1'
#330000
1$
0'
#335000
1'
#340000
0$
0'
#345000
1'
#350000
1$
0'
#355000
1'
#360000
1#
0$
0'
#365000
1'
#370000
1$
0'
#375000
1'
#380000
0#
0$
0'
#385000
1'
#390000
1$
0'
#395000
1'
#400000
0$
0'
#405000
1'
#410000
1$
0'
#415000
1'
#420000
1#
0$
0'
#425000
1'
#430000
1$
0'
#435000
1'
#440000
0$
0'
#445000
0#
1%
1'
#450000
0'
#455000
1'
#460000
0'
#465000
1'
#470000
0'
#475000
1'
#480000
0'
#485000
1'
#490000
0'
#495000
0%
1'
#500000
1$
0'
#505000
1'
#510000
1#
0$
0'
#515000
1'
#520000
1$
0'
#525000
1'
#530000
0#
0$
0'
#535000
1'
#540000
1$
0'
#545000
1'
#550000
0$
0'
#555000
1'
#560000
1$
0'
#565000
1'
#570000
0$
0'
#575000
1'
#580000
1$
0'
#585000
1'
#590000
1#
0$
0'
#595000
1'
#600000
1$
0'
#605000
1'
#610000
0#
0$
0'
#615000
1'
#620000
1$
0'
#625000
1'
#630000
0$
0'
#635000
1'
#640000
1$
0'
#645000
1'
#650000
1#
0$
0'
#655000
1'
#660000
1$
0'
#665000
1'
#670000
0$
0'
#675000
0#
1%
1'
#680000
0'
#685000
1'
#690000
0'
#695000
1'
#700000
0'
#705000
1'
#710000
0'
#715000
1'
#720000
0'
#725000
0%
1'
#730000
1$
0'
#735000
1'
#740000
1#
0$
0'
#745000
1'
#750000
1$
0'
#755000
1'
#760000
0#
0$
0'
#765000
1'
#770000
1$
0'
#775000
1'
#780000
0$
0'
#785000
1'
#790000
1$
0'
#795000
1'
#800000
0$
0'
